dicomweb_client/__init__.py
dicomweb_client/api.py
dicomweb_client/cli.py
dicomweb_client/error.py
dicomweb_client/log.py
dicomweb_client/data/file.dcm
dicomweb_client/data/retrieve_instance_metadata.json
dicomweb_client/data/retrieve_instance_pixeldata.jp2
dicomweb_client/data/retrieve_instance_pixeldata.jpg
dicomweb_client/data/retrieve_instance_pixeldata.png
dicomweb_client/data/search_for_instances.json
dicomweb_client/data/search_for_series.json
dicomweb_client/data/search_for_studies.json
dicomweb_client/data/search_for_studies_limit-2_offset-1.json
dicomweb_client/tests/conftest.py
dicomweb_client/tests/test_api.py
dicomweb_client/tests/test_cli.py
clindatsci_orthanc_client-0.1.1.dist-info/LICENSE
clindatsci_orthanc_client-0.1.1.dist-info/METADATA
clindatsci_orthanc_client-0.1.1.dist-info/WHEEL
clindatsci_orthanc_client-0.1.1.dist-info/entry_points.txt
clindatsci_orthanc_client-0.1.1.dist-info/top_level.txt
clindatsci_orthanc_client-0.1.1.dist-info/RECORD
