Metadata-Version: 2.1
Name: clindatsci-orthanc-client
Version: 0.1.1
Summary: Client for DICOMweb RESTful services (dicomweb-client patch for Orthanc 1.5.7).
Home-page: https://github.com/seandoyle/dicomweb-client
Author: Markus D. Herrmann (republished by Sean Doyle)
Maintainer: Markus D. Herrmann (republished by Sean Doyle)
License: MIT
Platform: Linux
Platform: MacOS
Platform: Windows
Classifier: Environment :: Web Environment
Classifier: License :: OSI Approved :: MIT License
Classifier: Operating System :: MacOS
Classifier: Operating System :: Microsoft :: Windows
Classifier: Operating System :: POSIX :: Linux
Classifier: Intended Audience :: Science/Research
Classifier: Topic :: Internet :: WWW/HTTP
Classifier: Topic :: Multimedia :: Graphics
Classifier: Topic :: Scientific/Engineering :: Information Analysis
Classifier: Programming Language :: Python :: 3
Classifier: Development Status :: 4 - Beta
Requires-Dist: numpy (>=1.13)
Requires-Dist: pillow (>=5.0)
Requires-Dist: pydicom (>=1.0)
Requires-Dist: requests (>=2.18)
Requires-Dist: six (>=1.11)
Provides-Extra: docs
Requires-Dist: sphinx (>=1.7.1) ; extra == 'docs'
Requires-Dist: sphinx-pyreverse (>=0.0.12) ; extra == 'docs'
Requires-Dist: sphinxcontrib-autoprogram (>=0.1.4) ; extra == 'docs'
Requires-Dist: sphinx-rtd-theme (>=0.2.4) ; extra == 'docs'
Provides-Extra: gcp
Requires-Dist: google-auth (>=1.6) ; extra == 'gcp'
Requires-Dist: google-oauth (>=1.0) ; extra == 'gcp'
